mindsql/__init__.py
mindsql/_helper/__init__.py
mindsql/_helper/helper.py
mindsql/_utils/__init__.py
mindsql/_utils/constants.py
mindsql/_utils/logger.py
mindsql/_utils/prompts.py
mindsql/core/__init__.py
mindsql/core/mindsql_core.py
mindsql/databases/__init__.py
mindsql/databases/idatabase.py
mindsql/databases/mysql.py
mindsql/databases/postgres.py
mindsql/databases/sqlite.py
mindsql/llms/__init__.py
mindsql/llms/googlegenai.py
mindsql/llms/illm.py
mindsql/llms/llama.py
mindsql/llms/open_ai.py
mindsql/vectorstores/__init__.py
mindsql/vectorstores/chromadb.py
mindsql/vectorstores/faiss_db.py
mindsql/vectorstores/ivectorstore.py
mindsql-0.2.1.dist-info/LICENSE
mindsql-0.2.1.dist-info/METADATA
mindsql-0.2.1.dist-info/WHEEL
mindsql-0.2.1.dist-info/RECORD
