Metadata-Version: 2.1
Name: mindsql
Version: 0.2.1
Summary: Text-2-SQL made easy in just a few lines of python.
Home-page: https://www.mindinventory.com/text-to-sql-mindsql.php
License: GPL-3.0-or-later
Keywords: Text2SQL,data,text to sql,Text-to-SQL,RAG,LLM,NLP
Author: Mindinventory
Author-email: info@mindinventory.com
Requires-Python: >=3.10,<4.0
Classifier: License :: OSI Approved :: GNU General Public License v3 or later (GPLv3+)
Classifier: Programming Language :: Python :: 3
Classifier: Programming Language :: Python :: 3.10
Classifier: Programming Language :: Python :: 3.11
Classifier: Programming Language :: Python :: 3.12
Classifier: Topic :: Scientific/Engineering :: Artificial Intelligence
Classifier: Topic :: Software Development :: Libraries :: Application Frameworks
Classifier: Topic :: Software Development :: Libraries :: Python Modules
Requires-Dist: chromadb (>=0.4.22,<0.5.0)
Requires-Dist: faiss-cpu (>=1.8.0,<2.0.0)
Requires-Dist: google-generativeai (==0.3.2)
Requires-Dist: llama-cpp-python (==0.2.47)
Requires-Dist: mysql-connector-python (>=8.3.0,<9.0.0)
Requires-Dist: numpy (>=1.26.4,<2.0.0)
Requires-Dist: openai (>=1.12.0,<2.0.0)
Requires-Dist: pandas (==2.2.0)
Requires-Dist: plotly (==5.19.0)
Requires-Dist: psycopg2-binary (>=2.9.9,<3.0.0)
Requires-Dist: pysqlite3-binary (>=0.5.2.post3,<0.6.0)
Requires-Dist: sentence-transformers (>=2.3.1,<3.0.0)
Requires-Dist: sqlparse (>=0.4.4,<0.5.0)
Project-URL: Repository, https://github.com/Mindinventory/MindSQL
